frame_search/__init__.py
frame_search/extension.py
frame_search/pandas.py
frame_search/polars.py
frame_search/search.py
frame_search-0.2.0.dist-info/METADATA
frame_search-0.2.0.dist-info/WHEEL
frame_search-0.2.0.dist-info/RECORD
