Metadata-Version: 2.4
Name: frame-search
Version: 0.2.0
Summary: Query dataframes with GitHub search syntax
Author-email: Will Dean <wd60622@gmail.com>
Requires-Python: >=3.9
Requires-Dist: narwhals
